README.md
setup.py
Abyss_Beta.egg-info/PKG-INFO
Abyss_Beta.egg-info/SOURCES.txt
Abyss_Beta.egg-info/dependency_links.txt
Abyss_Beta.egg-info/requires.txt
Abyss_Beta.egg-info/top_level.txt
Nebula/Abyss.py
Nebula/Nebula.py
Nebula/NebulaCore.py
Nebula/NebulaObject.py
Nebula/__init__.py
Nebula/_autoCFG.py
Nebula/_setup.py